04/my_ha.v
module my_ha(a, b, r, c);
input a, b;
output r, c;

    assign r = (a & ~b) | (~a & b);
    assign c = a & b;

endmodule

04/my_fa.v
module my_fa(cin, a, b, r, cout);
input cin, a, b;
output r, cout;
wire r1, c1, c2;

    my_ha ha1(.a(a), .b(b), .r(r1), .c(c1));
    my_ha ha2(.a(r1), .b(cin), .r(r), .c(c2));

    assign cout = c1 | c2;

endmodule

04/test_my_fa.v
module test_my_fa;
reg in1, in2, in3;
wire out1, out2;
my_fa mn1 (.a(in1), .b(in2), .cin(in3), .r(out1), .cout(out2));
initial begin
    $dumpfile("test_my_fa.vcd");
    $dumpvars(0, test_my_fa);
    $monitor ("%t: in1 = %b, in2 = %b, in3 = %b, out1 = %b, out2 = %b", $time, in1, in2, in3, out1, out2);

    in1 = 0; in2 = 0; in3 = 0;

    #10 in3 = 1;
    #10 in2 = 1; in3 = 0;
    #10 in3 = 1;
    #10 in1 = 1; in2 = 0; in3 = 0;
    #10 in3 = 1;
    #10 in2 = 1; in3 = 0;
    #10 in3 = 1;
    $finish;
end
endmodule

04/test_my_fa.vcd
$date
	Tue Oct 29 11:56:55 2024
$end
$version
	Icarus Verilog
$end
$timescale
	1s
$end
$scope module test_my_fa $end
$var wire 1 ! out2 $end
$var wire 1 " out1 $end
$var reg 1 # in1 $end
$var reg 1 $ in2 $end
$var reg 1 % in3 $end
$scope module mn1 $end
$var wire 1 # a $end
$var wire 1 $ b $end
$var wire 1 % cin $end
$var wire 1 ! cout $end
$var wire 1 & r1 $end
$var wire 1 " r $end
$var wire 1 ' c2 $end
$var wire 1 ( c1 $end
$scope module ha1 $end
$var wire 1 # a $end
$var wire 1 $ b $end
$var wire 1 ( c $end
$var wire 1 & r $end
$upscope $end
$scope module ha2 $end
$var wire 1 & a $end
$var wire 1 % b $end
$var wire 1 ' c $end
$var wire 1 " r $end
$upscope $end
$upscope $end
$upscope $end
$enddefinitions $end
$comment Show the parameter values. $end
$dumpall
$end
#0
$dumpvars
0(
0'
0&
0%
0$
0#
0"
0!
$end
#10
1"
1%
#20
1"
1&
0%
1$
#30
0"
1!
1'
1%
#40
1"
0!
1&
0'
0%
0$
1#
#50
0"
1!
1'
1%
#60
0"
0&
0'
1(
0%
1$
#70
1"
1%
